mcp_auto_builder/__init__.py
mcp_auto_builder/main.py
mcp_auto_builder-0.1.0.dist-info/METADATA
mcp_auto_builder-0.1.0.dist-info/WHEEL
mcp_auto_builder-0.1.0.dist-info/top_level.txt
mcp_auto_builder-0.1.0.dist-info/RECORD
