Metadata-Version: 2.4
Name: mcp-auto_builder
Version: 0.1.0
Summary: Final unified interface for global users
Home-page: https://github.com/Sumedh99/mcp_auto_builder
Author: Sumedh99
Author-email: Sumedh99@users.noreply.github.com
Classifier: Programming Language :: Python :: 3
Classifier: License :: OSI Approved :: MIT License
Classifier: Operating System :: OS Independent
Requires-Python: >=3.7
Dynamic: author
Dynamic: author-email
Dynamic: classifier
Dynamic: description
Dynamic: description-content-type
Dynamic: home-page
Dynamic: requires-python
Dynamic: summary
